chrplotlib/__init__.py
chrplotlib/animation.py
chrplotlib/bar.py
chrplotlib/img.py
chrplotlib-0.1.1.dist-info/LICENSE
chrplotlib-0.1.1.dist-info/METADATA
chrplotlib-0.1.1.dist-info/WHEEL
chrplotlib-0.1.1.dist-info/top_level.txt
chrplotlib-0.1.1.dist-info/RECORD
