Metadata-Version: 2.1
Name: chrplotlib
Version: 0.1.1
Summary: Plot in chars
Home-page: https://github.com/guofei9987/chrplotlib
Author: Guo Fei
Author-email: guofei9987@foxmail.com
License: MIT
Platform: linux
Platform: windows
Platform: macos
Requires-Python: >=3.5
License-File: LICENSE
